nautiluszim/VERSION
nautiluszim/__about__.py
nautiluszim/__init__.py
nautiluszim/constants.py
nautiluszim/entrypoint.py
nautiluszim/scraper.py
nautiluszim/locale/fr/LC_MESSAGES/messages.po
nautiluszim/templates/database.js
nautiluszim/templates/display_rows.handlebars
nautiluszim/templates/favicon.png
nautiluszim/templates/home.html
nautiluszim/templates/info-circle-solid.svg
nautiluszim/templates/init.js
nautiluszim/templates/main-logo.png
nautiluszim/templates/media_player.handlebars
nautiluszim/templates/modal_empty_body.handlebars
nautiluszim/templates/modal_title.handlebars
nautiluszim/templates/nautilus.js
nautiluszim/templates/styles.css
nautiluszim-1.2.1.dist-info/METADATA
nautiluszim-1.2.1.dist-info/WHEEL
nautiluszim-1.2.1.dist-info/entry_points.txt
nautiluszim-1.2.1.dist-info/licenses/LICENSE
nautiluszim-1.2.1.dist-info/RECORD
