Metadata-Version: 2.1
Name: nautiluszim
Version: 1.2.1
Summary: turns a collection of documents into a browsable ZIM file
Project-URL: Donate, https://www.kiwix.org/en/support-us/
Project-URL: Homepage, https://github.com/openzim/nautilus
Author-email: openZIM <dev@openzim.org>
License: GPL-3.0-or-later
License-File: LICENSE
Keywords: offline,openzim,zim
Classifier: License :: OSI Approved :: GNU General Public License v3 or later (GPLv3+)
Classifier: Programming Language :: Python :: 3
Classifier: Programming Language :: Python :: 3.11
Classifier: Programming Language :: Python :: 3.12
Requires-Python: <3.13,>=3.11
Requires-Dist: jinja2==3.1.4
Requires-Dist: zimscraperlib==3.3.2
Provides-Extra: check
Requires-Dist: pyright==1.1.362; extra == 'check'
Provides-Extra: dev
Requires-Dist: ipython==8.24.0; extra == 'dev'
Requires-Dist: nautiluszim[check]; extra == 'dev'
Requires-Dist: nautiluszim[lint]; extra == 'dev'
Requires-Dist: nautiluszim[scripts]; extra == 'dev'
Requires-Dist: nautiluszim[test]; extra == 'dev'
Requires-Dist: pre-commit==3.7.0; extra == 'dev'
Provides-Extra: lint
Requires-Dist: black==24.4.2; extra == 'lint'
Requires-Dist: ruff==0.4.4; extra == 'lint'
Provides-Extra: scripts
Requires-Dist: invoke==2.2.0; extra == 'scripts'
Provides-Extra: test
Requires-Dist: coverage==7.5.1; extra == 'test'
Requires-Dist: pytest==8.2.0; extra == 'test'
